{
  "kind": "coverage_report",
  "version": "1.0",
  "generatedAt": "2026-02-04T11:39:04.300Z",
  "sources": {
    "buildRequest": true,
    "implementationPlan": true
  },
  "requirements": {
    "total": 1,
    "implemented": 1,
    "items": [
      {
        "id": "REQ-1",
        "summary": "Adjust the planned-moment pill card styling so the card appears significantly narrower (reduced height/thickness) and more elongated horizontally, while preserving the existing border-only pill look, left color dot, and right-side action icons. Implement this by updating the CSS for the planned-moment card classes used by `frontend/src/components/PlannedMomentCard.tsx` (e.g., `.planned-moment-card-clear`, `.planned-moment-card-color-dot`, and related action/icon sizing/spacing) in `frontend/src/index.css`.",
        "status": "implemented",
        "plannedFiles": [
          "frontend/src/index.css"
        ],
        "matchedFiles": [
          "frontend/src/index.css"
        ]
      }
    ]
  },
  "changedFiles": [
    "build-request.json",
    "feature_evidence.json",
    "frontend-file-summaries.txt",
    "frontend-implementation-plan.json",
    "frontend/src/index.css",
    "project_state.json",
    "scratch/component-selection.json",
    "spec.md",
    "spec_vs_diff_report.json"
  ]
}